envelope/__init__.py
envelope/forms.py
envelope/models.py
envelope/settings.py
envelope/signals.py
envelope/spam_filters.py
envelope/urls.py
envelope/views.py
envelope/locale/el/LC_MESSAGES/django.mo
envelope/locale/el/LC_MESSAGES/django.po
envelope/locale/es/LC_MESSAGES/django.mo
envelope/locale/es/LC_MESSAGES/django.po
envelope/locale/fi/LC_MESSAGES/django.mo
envelope/locale/fi/LC_MESSAGES/django.po
envelope/locale/fr/LC_MESSAGES/django.mo
envelope/locale/fr/LC_MESSAGES/django.po
envelope/locale/lv/LC_MESSAGES/django.mo
envelope/locale/lv/LC_MESSAGES/django.po
envelope/locale/nl/LC_MESSAGES/django.mo
envelope/locale/nl/LC_MESSAGES/django.po
envelope/locale/pl/LC_MESSAGES/django.mo
envelope/locale/pl/LC_MESSAGES/django.po
envelope/locale/pt_BR/LC_MESSAGES/django.mo
envelope/locale/pt_BR/LC_MESSAGES/django.po
envelope/locale/ru/LC_MESSAGES/django.mo
envelope/locale/ru/LC_MESSAGES/django.po
envelope/templates/envelope/contact_form.html
envelope/templates/envelope/email_body.html
envelope/templates/envelope/email_body.txt
envelope/templatetags/__init__.py
envelope/templatetags/envelope_tags.py
django_envelope-1.4.dist-info/AUTHORS.rst
django_envelope-1.4.dist-info/LICENSE
django_envelope-1.4.dist-info/METADATA
django_envelope-1.4.dist-info/WHEEL
django_envelope-1.4.dist-info/top_level.txt
django_envelope-1.4.dist-info/RECORD
